mayatk/__init__.py
mayatk/anim_utils/__init__.py
mayatk/anim_utils/_anim_utils.py
mayatk/anim_utils/playblast_exporter.py
mayatk/anim_utils/scale_keys.py
mayatk/anim_utils/segment_keys.py
mayatk/anim_utils/stagger_keys.py
mayatk/anim_utils/unbake_keys.py
mayatk/cam_utils/__init__.py
mayatk/cam_utils/_cam_utils.py
mayatk/core_utils/__init__.py
mayatk/core_utils/_core_utils.py
mayatk/core_utils/components.py
mayatk/core_utils/mash.py
mayatk/core_utils/preview.py
mayatk/core_utils/diagnostics/__init__.py
mayatk/core_utils/diagnostics/animation_diag.py
mayatk/core_utils/diagnostics/mesh_diag.py
mayatk/core_utils/diagnostics/scene_diag.py
mayatk/core_utils/diagnostics/transform_diag.py
mayatk/core_utils/diagnostics/uv_diag.py
mayatk/core_utils/instancing/__init__.py
mayatk/core_utils/instancing/assembly_reconstructor.py
mayatk/core_utils/instancing/assembly_reconstructor_simple.py
mayatk/core_utils/instancing/assembly_reconstructor_v10.py
mayatk/core_utils/instancing/assembly_reconstructor_v2.py
mayatk/core_utils/instancing/assembly_reconstructor_v3.py
mayatk/core_utils/instancing/assembly_reconstructor_v4.py
mayatk/core_utils/instancing/assembly_reconstructor_v5.py
mayatk/core_utils/instancing/assembly_reconstructor_v6.py
mayatk/core_utils/instancing/assembly_reconstructor_v7.py
mayatk/core_utils/instancing/assembly_reconstructor_v8.py
mayatk/core_utils/instancing/assembly_reconstructor_v9.py
mayatk/core_utils/instancing/auto_instancer.py
mayatk/core_utils/instancing/geometry_matcher.py
mayatk/core_utils/instancing/instancing_strategy.py
mayatk/display_utils/__init__.py
mayatk/display_utils/_display_utils.py
mayatk/display_utils/color_manager.py
mayatk/display_utils/color_manager.ui
mayatk/display_utils/exploded_view.py
mayatk/display_utils/exploded_view.ui
mayatk/edit_utils/__init__.py
mayatk/edit_utils/_edit_utils.py
mayatk/edit_utils/bevel.py
mayatk/edit_utils/bevel.ui
mayatk/edit_utils/bridge.py
mayatk/edit_utils/bridge.ui
mayatk/edit_utils/cut_on_axis.py
mayatk-0.9.73.dist-info/licenses/LICENSE
mayatk-0.9.73.dist-info/METADATA
mayatk-0.9.73.dist-info/WHEEL
mayatk-0.9.73.dist-info/top_level.txt
mayatk-0.9.73.dist-info/RECORD
