Metadata-Version: 2.4
Name: mayatk
Version: 0.9.73
Summary: A comprehensive toolkit for Autodesk Maya providing utilities for modeling, animation, rigging, and UI management.
Author-email: Ryan Simpson <m3trik@outlook.com>
License: MIT
Project-URL: Homepage, https://github.com/m3trik/mayatk
Project-URL: Repository, https://github.com/m3trik/mayatk
Classifier: Programming Language :: Python :: 3
Classifier: License :: OSI Approved :: MIT License
Classifier: Operating System :: OS Independent
Requires-Python: >=3.9
License-File: LICENSE
Requires-Dist: pythontk>=0.7.67
Requires-Dist: uitk>=1.0.66
Dynamic: license-file
